{
    "constructors": [
        {
            "id": "253890367",
            "predicate": "unknown_3f0f220f",
            "params": [
                {
                    "name": "flags",
                    "type": "#"
                },
                {
                    "name": "user",
                    "type": "user"
                },
                {
                    "name": "contactsLink",
                    "type": "ContactsMyLink"
                },
                {
                    "name": "photo",
                    "type": "flags.2?PhotoLayer82"
                },
                {
                    "name": "peerNotifySettings",
                    "type": "flags.4?PeerNotifySettings"
                },
                {
                    "name": "unknown",
                    "type": "int"
                }
            ]
        },
        {
            "id": "-775091636",
            "predicate": "contacts.importedContacts",
            "params": [
                {
                    "name": "imported",
                    "type": "Vector<ImportedContact>"
                },
                {
                    "name": "users",
                    "type": "Vector<User>"
                }
            ],
            "type": "contacts.ImportedContacts"
        },
        {
            "id": "-1434994573",
            "predicate": "contactStatus",
            "params": [
                {
                    "name": "user_id",
                    "type": "int"
                },
                {
                    "name": "was_online",
                    "type": "int"
                }
            ],
            "type": "ContactStatus"
        },
        {
            "id": "590174469",
            "predicate": "config",
            "params": [
                {
                    "name": "date",
                    "type": "int"
                },
                {
                    "name": "test_mode",
                    "type": "Bool"
                },
                {
                    "name": "this_dc",
                    "type": "int"
                },
                {
                    "name": "dc_options",
                    "type": "Vector<DcOption>"
                },
                {
                    "name": "chat_size_max",
                    "type": "int"
                }
            ],
            "type": "Config"
        },
        {
            "id": "571849917",
            "predicate": "auth.sentCode",
            "params": [
                {
                    "name": "phone_registered",
                    "type": "Bool"
                },
                {
                    "name": "phone_code_hash",
                    "type": "string"
                }
            ],
            "type": "auth.SentCode"
        },
        {
            "id": "-635250259",
            "predicate": "updateUserName",
            "params": [
                {
                    "name": "user_id",
                    "type": "int"
                },
                {
                    "name": "first_name",
                    "type": "string"
                },
                {
                    "name": "unknown_static_digit",
                    "type": "long"
                }
            ],
            "type": "Update"
        },
        {
            "id": "-1148475897",
            "predicate": "updateUserPhoto",
            "params": [
                {
                    "name": "user_id",
                    "type": "int"
                },
                {
                    "name": "photo",
                    "type": "UserProfilePhoto"
                }
            ],
            "type": "Update"
        },
        {
            "id": "-1657903163",
            "predicate": "contacts.updateContactLink",
            "params": [
                {
                    "name": "user_id",
                    "type": "int"
                },
                {
                    "name": "my_link",
                    "type": "MyLink"
                },
                {
                    "name": "foreign_link",
                    "type": "ForeignLink"
                }
            ]
        },
        {
            "id": "646922073",
            "predicate": "contacts.myLinkHasPhone",
            "params": []
        },
        {
            "id": "955951967",
            "predicate": "auth.sentCode",
            "params": [
                {
                    "name": "flags",
                    "type": "int"
                },
                {
                    "name": "type",
                    "type": "auth.SentCodeType"
                },
                {
                    "name": "phone_code_hash",
                    "type": "string"
                },
                {
                    "name": "next_type",
                    "type": "flags.1?auth.CodeType"
                },
                {
                    "name": "timeout",
                    "type": "flags.2?int"
                },
                {
                    "name": "terms_of_service",
                    "type": "flags.3?help.termsOfService"
                }
            ],
            "type": "auth.SentCode"
        },
        {
            "id": "292985073",
            "predicate": "langpack.langPackLanguage",
            "params": [
                {
                    "name": "lang_code",
                    "type": "string"
                },
                {
                    "name": "name",
                    "type": "string"
                },
                {
                    "name": "native_name",
                    "type": "string"
                }
            ]
        },
        {
            "id": "840162234",
            "predicate": "help.Config",
            "params": [
                {
                    "name": "flags",
                    "type": "int"
                },
                {
                    "name": "date",
                    "type": "int"
                },
                {
                    "name": "expires",
                    "type": "int"
                },
                {
                    "name": "test_mode",
                    "type": "Bool"
                },
                {
                    "name": "this_dc",
                    "type": "int"
                },
                {
                    "name": "dc_option",
                    "type": "Vector<dcOption>"
                },
                {
                    "name": "dc_txt_domain_name",
                    "type": "string"
                },
                {
                    "name": "chat_size_max",
                    "type": "int"
                },
                {
                    "name": "megagroup_size_max",
                    "type": "int"
                },
                {
                    "name": "forwarded_count_max",
                    "type": "int"
                },
                {
                    "name": "online_update_period_ms",
                    "type": "int"
                },
                {
                    "name": "offline_blur_timeout_ms",
                    "type": "int"
                },
                {
                    "name": "offline_idle_timeout_ms",
                    "type": "int"
                },
                {
                    "name": "online_cloud_timeout_ms",
                    "type": "int"
                },
                {
                    "name": "notify_cloud_delay_ms",
                    "type": "int"
                },
                {
                    "name": "notify_default_delay_ms",
                    "type": "int"
                },
                {
                    "name": "push_chat_period_ms",
                    "type": "int"
                },
                {
                    "name": "push_chat_limit",
                    "type": "int"
                },
                {
                    "name": "saved_gifs_limit",
                    "type": "int"
                },
                {
                    "name": "edit_time_limit",
                    "type": "int"
                },
                {
                    "name": "revoke_time_limit",
                    "type": "int"
                },
                {
                    "name": "revoke_pm_time_limit",
                    "type": "int"
                },
                {
                    "name": "rating_e_decay",
                    "type": "int"
                },
                {
                    "name": "stickers_recent_limit",
                    "type": "int"
                },
                {
                    "name": "stickers_faved_limit",
                    "type": "int"
                },
                {
                    "name": "channels_read_media_period",
                    "type": "int"
                },
                {
                    "name": "tmp_sessions",
                    "type": "flags.0?int"
                },
                {
                    "name": "pinned_dialogs_count_max",
                    "type": "int"
                },
                {
                    "name": "call_receive_timeout_ms",
                    "type": "int"
                },
                {
                    "name": "call_ring_timeout_ms",
                    "type": "int"
                },
                {
                    "name": "call_connect_timeout_ms",
                    "type": "int"
                },
                {
                    "name": "call_packet_timeout_ms",
                    "type": "int"
                },
                {
                    "name": "me_url_prefix",
                    "type": "string"
                },
                {
                    "name": "autoupdate_url_prefix",
                    "type": "flags.7?string"
                },
                {
                    "name": "gif_search_username",
                    "type": "flags.9?string"
                },
                {
                    "name": "venue_search_username",
                    "type": "flags.10?string"
                },
                {
                    "name": "img_search_username",
                    "type": "flags.11?string"
                },
                {
                    "name": "static_maps_provider",
                    "type": "flags.12?string"
                },
                {
                    "name": "caption_length_max",
                    "type": "int"
                },
                {
                    "name": "message_length_max",
                    "type": "int"
                },
                {
                    "name": "webfile_dc_id",
                    "type": "int"
                },
                {
                    "name": "suggested_lang_code",
                    "type": "flags.2?string"
                },
                {
                    "name": "lang_pack_version",
                    "type": "int"
                }
            ]
        },
        {
            "id": "808409587",
            "predicate": "auth.codeSettings",
            "params": [
                {
                    "name": "flags",
                    "type": "int"
                },
                {
                    "name": "app_hash",
                    "type": "flags.3?string"
                }
            ]
        }
    ],
    "methods": [
        {
            "id": "-781192334",
            "predicate": "auth.sendCode",
            "params": [
                {
                    "name": "phone_number",
                    "type": "string"
                },
                {
                    "name": "sms_type",
                    "type": "int"
                },
                {
                    "name": "api_id",
                    "type": "int"
                },
                {
                    "name": "api_hash",
                    "type": "string"
                }
            ],
            "type": "auth.SentCode"
        },
        {
            "id": "-1099002127",
            "predicate": "req_pq_multi",
            "params": [
                {
                    "name": "nonce",
                    "type": "int128"
                }
            ],
            "type": "ResPQ"
        },
        {
            "id": "1669245048",
            "predicate": "push.registerDevice",
            "params": [
                {
                    "name": "token_type",
                    "type": "int"
                },
                {
                    "name": "token",
                    "type": "string"
                }
            ]
        },
        {
            "id": "1555998096",
            "predicate": "push.registerDeviceJava",
            "params": [
                {
                    "name": "token_type",
                    "type": "int"
                },
                {
                    "name": "token",
                    "type": "string"
                },
                {
                    "name": "app_sandbox",
                    "type": "Bool"
                },
                {
                    "name": "secret",
                    "type": "string"
                },
                {
                    "name": "uids",
                    "type": "Vector<int>"
                }
            ]
        },
        {
            "id": "-422959626",
            "predicate": "help.Config",
            "params": [
                {
                    "name": "flags",
                    "type": "int"
                },
                {
                    "name": "date",
                    "type": "int"
                },
                {
                    "name": "expires",
                    "type": "int"
                },
                {
                    "name": "test_mode",
                    "type": "Bool"
                },
                {
                    "name": "this_dc",
                    "type": "int"
                },
                {
                    "name": "dc_option",
                    "type": "Vector<dcOption>"
                },
                {
                    "name": "dc_txt_domain_name",
                    "type": "string"
                },
                {
                    "name": "chat_size_max",
                    "type": "int"
                },
                {
                    "name": "megagroup_size_max",
                    "type": "int"
                },
                {
                    "name": "forwarded_count_max",
                    "type": "int"
                },
                {
                    "name": "online_update_period_ms",
                    "type": "int"
                },
                {
                    "name": "offline_blur_timeout_ms",
                    "type": "int"
                },
                {
                    "name": "offline_idle_timeout_ms",
                    "type": "int"
                },
                {
                    "name": "online_cloud_timeout_ms",
                    "type": "int"
                },
                {
                    "name": "notify_cloud_delay_ms",
                    "type": "int"
                },
                {
                    "name": "notify_default_delay_ms",
                    "type": "int"
                },
                {
                    "name": "push_chat_period_ms",
                    "type": "int"
                },
                {
                    "name": "push_chat_limit",
                    "type": "int"
                },
                {
                    "name": "saved_gifs_limit",
                    "type": "int"
                },
                {
                    "name": "edit_time_limit",
                    "type": "int"
                },
                {
                    "name": "revoke_time_limit",
                    "type": "int"
                },
                {
                    "name": "revoke_pm_time_limit",
                    "type": "int"
                },
                {
                    "name": "rating_e_decay",
                    "type": "int"
                },
                {
                    "name": "stickers_recent_limit",
                    "type": "int"
                },
                {
                    "name": "stickers_faved_limit",
                    "type": "int"
                },
                {
                    "name": "channels_read_media_period",
                    "type": "int"
                },
                {
                    "name": "tmp_sessions",
                    "type": "flags.0?int"
                },
                {
                    "name": "pinned_dialogs_count_max",
                    "type": "int"
                },
                {
                    "name": "call_receive_timeout_ms",
                    "type": "int"
                },
                {
                    "name": "call_ring_timeout_ms",
                    "type": "int"
                },
                {
                    "name": "call_connect_timeout_ms",
                    "type": "int"
                },
                {
                    "name": "call_packet_timeout_ms",
                    "type": "int"
                },
                {
                    "name": "me_url_prefix",
                    "type": "string"
                },
                {
                    "name": "autoupdate_url_prefix",
                    "type": "flags.7?string"
                },
                {
                    "name": "gif_search_username",
                    "type": "flags.9?string"
                },
                {
                    "name": "venue_search_username",
                    "type": "flags.10?string"
                },
                {
                    "name": "img_search_username",
                    "type": "flags.11?string"
                },
                {
                    "name": "static_maps_provider",
                    "type": "flags.12?string"
                },
                {
                    "name": "caption_length_max",
                    "type": "int"
                },
                {
                    "name": "message_length_max",
                    "type": "int"
                },
                {
                    "name": "webfile_dc_id",
                    "type": "int"
                },
                {
                    "name": "suggested_lang_code",
                    "type": "flags.2?string"
                },
                {
                    "name": "lang_pack_version",
                    "type": "flags.2?int"
                },
                {
                    "name": "lang_pack_version",
                    "type": "int"
                }
            ]
        },
        {
            "id": "-2035355412",
            "predicate": "auth.sendCode",
            "params": [
                {
                    "name": "flags",
                    "type": "int"
                },
                {
                    "name": "phone_number",
                    "type": "string"
                },
                {
                    "name": "current_number",
                    "type": "flags.0?Bool"
                },
                {
                    "name": "api_id",
                    "type": "int"
                },
                {
                    "name": "api_hash",
                    "type": "string"
                }
            ]
        },
        {
            "id": "-497756594",
            "predicate": "help.getPinnedDialogs",
            "params": []
        },
        {
            "id": "-1332171034",
            "predicate": "messages.getDialogs",
            "params": [
                {
                    "name": "flags",
                    "type": "int"
                },
                {
                    "name": "offset_date",
                    "type": "int"
                },
                {
                    "name": "offset_id",
                    "type": "int"
                },
                {
                    "name": "peer",
                    "type": "InputPeer"
                },
                {
                    "name": "limit",
                    "type": "int"
                },
                {
                    "name": "hash",
                    "type": "int"
                }
            ]
        }
    ]
}
